{
    "resnetv1d_layers1_conv1_weight": [
        8, 
        8, 
        3, 
        3
    ], 
    "resnetv1d_layers2_conv3_weight": [
        56, 
        128, 
        3, 
        3
    ], 
    "resnetv1d_down3_conv0_weight": [
        208, 
        56, 
        1, 
        1
    ], 
    "resnetv1d_layers3_conv2_weight": [
        256, 
        208, 
        3, 
        3
    ], 
    "resnetv1d_layers3_conv1_weight": [
        208, 
        256, 
        3, 
        3
    ], 
    "resnetv1d_conv0_weight": [
        8, 
        3, 
        7, 
        7
    ], 
    "resnetv1d_layers4_conv3_weight": [
        512, 
        512, 
        3, 
        3
    ], 
    "resnetv1d_down4_conv0_weight": [
        512, 
        208, 
        1, 
        1
    ], 
    "resnetv1d_layers3_conv0_weight": [
        256, 
        56, 
        3, 
        3
    ], 
    "resnetv1d_dense0_weight": [
        1000, 
        512
    ], 
    "resnetv1d_layers1_conv2_weight": [
        8, 
        8, 
        3, 
        3
    ], 
    "resnetv1d_dense0_bias": [
        1000
    ], 
    "resnetv1d_layers1_conv0_weight": [
        8, 
        8, 
        3, 
        3
    ], 
    "resnetv1d_layers2_conv1_weight": [
        56, 
        120, 
        3, 
        3
    ], 
    "resnetv1d_layers3_conv3_weight": [
        208, 
        256, 
        3, 
        3
    ], 
    "resnetv1d_layers4_conv1_weight": [
        512, 
        512, 
        3, 
        3
    ], 
    "resnetv1d_layers4_conv2_weight": [
        512, 
        512, 
        3, 
        3
    ], 
    "resnetv1d_layers2_conv2_weight": [
        128, 
        56, 
        3, 
        3
    ], 
    "resnetv1d_down2_conv0_weight": [
        56, 
        8, 
        1, 
        1
    ], 
    "resnetv1d_layers1_conv3_weight": [
        8, 
        8, 
        3, 
        3
    ], 
    "resnetv1d_layers4_conv0_weight": [
        512, 
        208, 
        3, 
        3
    ], 
    "resnetv1d_layers2_conv0_weight": [
        120, 
        8, 
        3, 
        3
    ]
}